walletweb3/__init__.py
walletweb3/walletweb3.py
walletweb3-0.1.1.dist-info/METADATA
walletweb3-0.1.1.dist-info/WHEEL
walletweb3-0.1.1.dist-info/top_level.txt
walletweb3-0.1.1.dist-info/RECORD
