Metadata-Version: 2.1
Name: walletweb3
Version: 0.1.1
Summary: web3 tool
Home-page: 
Author: bryan
Author-email: 
Classifier: Programming Language :: Python :: 3
Classifier: License :: OSI Approved :: MIT License
Requires-Python: >=3.7
